element_lab/__init__.py
element_lab/lab.py
element_lab/project.py
element_lab/version.py
element_lab/export/__init__.py
element_lab/export/nwb.py
element_lab-0.3.0.dist-info/LICENSE
element_lab-0.3.0.dist-info/METADATA
element_lab-0.3.0.dist-info/WHEEL
element_lab-0.3.0.dist-info/top_level.txt
element_lab-0.3.0.dist-info/RECORD
