Metadata-Version: 2.1
Name: element-lab
Version: 0.3.0
Summary: DataJoint Elements for Lab Management
Home-page: https://github.com/datajoint/element-lab
Author: DataJoint
Author-email: info@datajoint.com
License: MIT
Keywords: neuroscience lab management datajoint
Platform: UNKNOWN
License-File: LICENSE
Requires-Dist: datajoint (>=0.13.0)
